quartus/synthesis/alu.sv
/*
ALU.v
*/

module alu (
    input wire                            carry_in,
    input wire                      [7:0] input_a,
    input wire                      [7:0] input_b,
    input control_signals::alu_op_t       operation,

    output wire [7:0] alu_out,
    output wire       overflow_out,
    output wire       zero_out,
    output wire       negative_out,
    output wire       carry_out
);

  reg [8:0] result;

  assign alu_out = result[7:0];

  assign carry_out = result[8];
  assign negative_out = result[7];
  assign zero_out = ~|alu_out;
  assign overflow_out = (~input_a[7] & ~input_b[7] & result[7]) |
                       (input_a[7] & input_b[7] & ~result[7]) ;

  always_comb begin
    case (operation)
      control_signals::ALU_ADD: begin
        result = input_a + input_b + carry_in;
      end
      control_signals::ALU_SUB: begin
        result = input_a - input_b - carry_in;
      end
      control_signals::ALU_AND: begin
        result = input_a & input_b;
      end
      control_signals::ALU_OR: begin
        result = input_a | input_b;
      end
      control_signals::ALU_XOR: begin
        result = input_a ^ input_b;
      end
      control_signals::ALU_SHIFT_LEFT: begin
        result = (input_a << 1) + carry_in;
      end
      default: begin
        result = 8'b0;
      end
    endcase
  end

endmodule

quartus/testbenches/alu.test.sv
`timescale 1ns / 1ps

module alu_test ();
  reg                             carry_in;
  reg                       [7:0] input_a;
  reg                       [7:0] input_b;
  control_signals::alu_op_t       operation;
  reg                             flag_overflow;
  reg                             flag_zero;
  reg                             flag_neg;
  reg                             flag_carry;
  reg                       [7:0] alu_out;

  logic                           clk;
  initial clk = 1;
  always #10 clk = ~clk;

  alu alu (
      .carry_in(carry_in),
      .input_a(input_a),
      .input_b(input_b),
      .operation(operation),
      .overflow_out(flag_overflow),
      .zero_out(flag_zero),
      .negative_out(flag_neg),
      .carry_out(flag_carry),
      .alu_out(alu_out)
  );

  initial begin
    operation = control_signals::ALU_ADD;
    carry_in  = 1'b1;
    input_a   = 8'h5;
    input_b   = 8'h5;
    repeat (1) @(posedge clk);

    operation = control_signals::ALU_SUB;
    carry_in  = 1'b0;
    input_a   = 8'h4;
    input_b   = 8'h5;
    repeat (1) @(posedge clk);

    input_a = 8'h3;
    input_b = 8'h8;
    repeat (1) @(posedge clk);

    input_a = 8'h5;
    input_b = 8'h5;
    repeat (1) @(posedge clk);

    operation = control_signals::ALU_SHIFT_LEFT;
    input_a   = 8'b1100_0011;
    input_b   = 8'b1;
    repeat (1) @(posedge clk);

    $stop;
  end
endmodule

quartus/waveforms/alu.vcd
$date
	Tue Jul 16 19:28:14 2024
$end
$version
	ModelSim Version 2020.1
$end
$timescale
	1ps
$end
$scope module alu_test $end
$var reg 1 ! clk $end
$var reg 8 " alu_out [7:0] $end
$var reg 1 # carry_in $end
$var reg 1 $ flag_carry $end
$var reg 1 % flag_neg $end
$var reg 1 & flag_overflow $end
$var reg 1 ' flag_zero $end
$var reg 8 ( input_a [7:0] $end
$var reg 8 ) input_b [7:0] $end
$var integer 32 * operation $end
$upscope $end
$enddefinitions $end
#0
b1011 "
b1 #
b0 $
b0 %
b0 &
b0 '
b101 (
b101 )
bx0xxxxx *
b1 !
b0 %
b0 $
b0 '
b1011 "
b0 &
#10000
b0 !
#20000
b1 !
bx0xxxxx *
b0 #
b100 (
b1 &
b1 %
b1 $
b11111111 "
#30000
b0 !
#40000
b1 !
b11 (
b1000 )
b11111011 "
#50000
b0 !
#60000
b1 !
b101 (
b101 )
b0 &
b0 %
b0 $
b1 '
b0 "
#70000
b0 !
#80000
b1 !
bx0xxx1xxxx0xxx *
b11000011 (
b1 )
b1 %
b1 $
b0 '
b10000110 "
#90000
b0 !
#100000
b1 !
