quartus/synthesis/register.sv
module register (
    input  logic [7:0] data_in,
    output logic [7:0] data_out,

    input logic clk,
    input logic load,
    input logic reset
);
  reg [7:0] current_value;

  always @(posedge clk) begin
    if (reset) begin
      current_value <= 8'b0;
    end else if (load) begin
      current_value <= data_in;
    end else begin
      current_value <= current_value;
    end
  end

  assign data_out = current_value;

endmodule

quartus/synthesis/program_counter.sv
module program_counter (
    input wire [7:0] PCL_in,
    input wire [7:0] PCH_in,

    input wire clk,
    input wire inc_enable,
    input wire load,
    input wire reset,

    output wire [7:0] PCL_out,
    output wire [7:0] PCH_out

);

  reg [15:0] current_pc;

  assign PCL_out = current_pc[7:0];
  assign PCH_out = current_pc[15:8];

  always @(posedge clk) begin

    if (reset) begin
      current_pc <= 16'h0;
    end else if (load) begin
      current_pc <= {PCH_in, PCL_in};
    end else begin
      if (inc_enable) begin
        current_pc <= current_pc + 1'b1;
      end else begin
        current_pc <= current_pc;
      end
    end
  end

endmodule

quartus/synthesis/alu.sv
/*
ALU.v
*/

module alu (
    input wire                            carry_in,
    input wire                      [7:0] input_a,
    input wire                      [7:0] input_b,
    input control_signals::alu_op_t       operation,

    output wire [7:0] alu_out,
    output wire       overflow_out,
    output wire       zero_out,
    output wire       negative_out,
    output wire       carry_out
);

  reg [8:0] result;

  assign alu_out = result[7:0];

  assign carry_out = result[8];
  assign negative_out = result[7];
  assign zero_out = ~|alu_out;
  assign overflow_out = (~input_a[7] & ~input_b[7] & result[7]) |
                       (input_a[7] & input_b[7] & ~result[7]) ;

  always_comb begin
    case (operation)
      control_signals::ALU_ADD: begin
        result = input_a + input_b + carry_in;
      end
      control_signals::ALU_SUB: begin
        result = input_a - input_b - carry_in;
      end
      control_signals::ALU_AND: begin
        result = input_a & input_b;
      end
      control_signals::ALU_OR: begin
        result = input_a | input_b;
      end
      control_signals::ALU_XOR: begin
        result = input_a ^ input_b;
      end
      control_signals::ALU_SHIFT_LEFT: begin
        result = (input_a << 1) + carry_in;
      end
      default: begin
        result = 8'b0;
      end
    endcase
  end

endmodule

quartus/synthesis/cpu6502.sv
module cpu6502 (
    input logic reset,
    input logic clk_in,
    output logic READ_write,
    input logic [7:0] data_in,
    output logic [7:0] data_out,
    output logic [15:0] address_out
);


  typedef enum logic [31:0] {
    InstructionFetch,
    InstructionDecode,
    InstructionCycle2,
    InstructionCycle3,
    InstructionCycle4,
    InstructionCycle5,
    InstructionCycle6,

    InstructionStateEndMarker
  } instruction_state_t;

  // ---------------------------------------------------------
  // ------------------ CONTROL SIGNALS ----------------------
  // ---------------------------------------------------------
  logic ctrl_signals[control_signals::CtrlSignalEndMarker];
  instruction_state_t current_instr_state, next_instr_state;
  logic [7:0] current_instr;

  control_signals::alu_op_t alu_op;

  logic [7:0] data_in_latch;

  // ---------------------------------------------------------------
  // ------------------ Data and Address Buses ---------------------
  // ---------------------------------------------------------------

  bus_sources::data_bus_source_t current_data_bus_input;
  bus_sources::address_low_bus_source_t current_address_low_bus_input;
  bus_sources::address_high_bus_source_t current_address_high_bus_input;

  logic [7:0] data_bus, address_low_bus, address_high_bus;
  logic [7:0] data_bus_inputs[bus_sources::DataBusSrcEndMarker];
  logic [7:0] address_low_bus_inputs[bus_sources::AddressLowSrcEndMarker];
  logic [7:0] address_high_bus_inputs[bus_sources::AddressHighSrcEndMarker];

  assign data_bus = data_bus_inputs[current_data_bus_input];
  assign data_out = data_bus;
  assign address_low_bus = address_low_bus_inputs[current_address_low_bus_input];
  assign address_high_bus = address_high_bus_inputs[current_address_high_bus_input];
  assign address_out = {
    address_high_bus_inputs[current_address_high_bus_input],
    address_low_bus_inputs[current_address_low_bus_input]
  };
  assign data_bus_inputs[bus_sources::DataBusSrcDataIn] = data_in;
  assign data_bus_inputs[bus_sources::DataBusSrcFF] = 8'hff;

  // ---------------------------------------------------------------
  // ------------------ Datapath Components ------------------------
  // ---------------------------------------------------------------

  // GPR registers
  register RegAccumulator (
      .data_in(data_bus),
      .data_out(data_bus_inputs[bus_sources::DataBusSrcRegAccumulator]),
      .clk(clk_in),
      .load(ctrl_signals[control_signals::CtrlLoadAccumutator]),
      .reset(reset)
  );
  register RegX (
      .data_in(data_bus),
      .data_out(data_bus_inputs[bus_sources::DataBusSrcRegX]),
      .clk(clk_in),
      .load(ctrl_signals[control_signals::CtrlLoadX]),
      .reset(reset)
  );
  register RegY (
      .data_in(data_bus),
      .data_out(data_bus_inputs[bus_sources::DataBusSrcRegY]),
      .clk(clk_in),
      .load(ctrl_signals[control_signals::CtrlLoadY]),
      .reset(reset)
  );

  // ALU + registers
  logic [7:0] alu_input_a, alu_input_b;
  logic alu_overflow, alu_zero, alu_negative, alu_carry;
  register InputA (
      .data_in(data_bus),
      .data_out(alu_input_a),
      .clk(clk_in),
      .load(ctrl_signals[control_signals::CtrlLoadInputA]),
      .reset(reset)
  );
  register InputB (
      .data_in(data_bus),
      .data_out(alu_input_b),
      .clk(clk_in),
      .load(ctrl_signals[control_signals::CtrlLoadInputB]),
      .reset(reset)
  );

  alu alu (
      .carry_in(1'b0),
      .input_a(alu_input_a),
      .input_b(alu_input_b),
      .operation(alu_op),
      .alu_out(data_bus_inputs[bus_sources::DataBusSrcRegAluResult]),
      .overflow_out(alu_overflow),
      .zero_out(alu_zero),
      .negative_out(alu_negative),
      .carry_out(alu_carry)
  );

  // Program Counter
  logic [15:0] program_counter;
  assign program_counter = {
    address_high_bus_inputs[bus_sources::AddressHighSrcPcHigh],
    address_low_bus_inputs[bus_sources::AddressLowSrcPcLow]
  };
  program_counter ProgramCounter (
      .PCL_in(address_low_bus),
      .PCH_in(address_high_bus),
      .clk(clk_in),
      .inc_enable(ctrl_signals[control_signals::CtrlPcIncEnable]),
      .load(ctrl_signals[control_signals::CtrlPcLoad]),
      .reset(reset),
      .PCL_out(address_low_bus_inputs[bus_sources::AddressLowSrcPcLow]),
      .PCH_out(address_high_bus_inputs[bus_sources::AddressHighSrcPcHigh])
  );

  // Instruction Register
  instruction_set::opcode_t instruction_register;
  register InstructionRegister (
      .data_in(data_bus),
      // Expliciting telling to pass every bit to cast the enum reg into a reg
      .data_out(instruction_register[7:0]),
      .clk(clk_in),
      .load(ctrl_signals[control_signals::CtrlLoadInstReg]),
      .reset(reset)
  );

  // --------------------------------------------------------
  // ------------------ CONTROL LOGIC -----------------------
  // --------------------------------------------------------

  always_ff @(posedge clk_in) begin
    data_in_latch <= data_in;
    if (reset) begin
      current_instr_state <= InstructionFetch;
    end else begin
      current_instr_state <= next_instr_state;
    end
  end

  always_comb begin
    ctrl_signals[control_signals::CtrlLoadAccumutator] = 0;
    ctrl_signals[control_signals::CtrlLoadX] = 0;
    ctrl_signals[control_signals::CtrlLoadY] = 0;
    ctrl_signals[control_signals::CtrlLoadInputA] = 0;
    ctrl_signals[control_signals::CtrlLoadInputB] = 0;
    ctrl_signals[control_signals::CtrlPcLoad] = 0;
    ctrl_signals[control_signals::CtrlLoadInstReg] = 0;
    ctrl_signals[control_signals::CtrlPcIncEnable] = 0;

    alu_op = control_signals::ALU_ADD;

    READ_write = 1;

    next_instr_state = current_instr_state;
    current_data_bus_input = bus_sources::DataBusSrcDataIn;
    current_address_low_bus_input = bus_sources::AddressLowSrcPcLow;
    current_address_high_bus_input = bus_sources::AddressHighSrcPcHigh;

    case (current_instr_state)
      InstructionFetch: begin
        next_instr_state = InstructionDecode;
        ctrl_signals[control_signals::CtrlLoadInstReg] = 1;
        ctrl_signals[control_signals::CtrlPcIncEnable] = 1;
      end
      InstructionDecode: begin
        ctrl_signals[control_signals::CtrlPcIncEnable] = 1;
        case (instruction_register)
          instruction_set::OpcNOP: begin
            next_instr_state = InstructionFetch;
          end
          instruction_set::OpcLDA_imm: begin
            next_instr_state = InstructionFetch;
            ctrl_signals[control_signals::CtrlLoadAccumutator] = 1;
          end
          instruction_set::OpcADC_imm: begin
            next_instr_state = InstructionCycle2;
            ctrl_signals[control_signals::CtrlLoadInputA] = 1;
          end
        endcase
      end
      InstructionCycle2: begin
        case (instruction_register)
          instruction_set::OpcADC_imm: begin
            next_instr_state = InstructionCycle3;
            current_data_bus_input = bus_sources::DataBusSrcRegAccumulator;
            ctrl_signals[control_signals::CtrlLoadInputB] = 1;
          end
        endcase
      end
      InstructionCycle3: begin
        case (instruction_register)
          instruction_set::OpcADC_imm: begin
            next_instr_state = InstructionCycle4;
            current_data_bus_input = bus_sources::DataBusSrcRegAccumulator;
            ctrl_signals[control_signals::CtrlLoadInputB] = 1;
          end
        endcase
      end
      InstructionCycle4: begin
        next_instr_state = InstructionFetch;
        current_data_bus_input = bus_sources::DataBusSrcRegAluResult;
        ctrl_signals[control_signals::CtrlLoadAccumutator] = 1;
      end
    endcase
  end


endmodule

quartus/testbenches/cpu6502.test.sv
module cpu6502_test ();
  logic clk;
  initial clk = 1;
  always #10 clk = ~clk;

  logic reset;
  logic READ_write;
  logic [7:0] data_in, data_out;
  logic [15:0] address_out;

  cpu6502 cpu6502 (
      .reset      (reset),
      .clk_in     (clk),
      .READ_write (READ_write),
      .data_in    (data_in),
      .data_out   (data_out),
      .address_out(address_out)
  );

  initial begin
    reset   = 1;
    data_in = instruction_set::OpcNOP;
    repeat (1) @(posedge clk);
    reset = 0;
    repeat (1) @(posedge clk);
    data_in = instruction_set::OpcLDA_imm;
    repeat (2) @(posedge clk);
    data_in = 8'h20;
    repeat (1) @(posedge clk);
    data_in = instruction_set::OpcADC_imm;
    repeat (1) @(posedge clk);
    data_in = 8'h5;
    repeat (10) @(posedge clk);

    $stop;
  end

endmodule

quartus/waveforms/cpu.vcd
$date
	Wed Jul 17 20:13:07 2024
$end
$version
	ModelSim Version 2020.1
$end
$timescale
	1ns
$end
$scope module cpu6502_test $end
$var reg 1 ! clk $end
$var reg 1 " reset $end
$var reg 1 # READ_write $end
$var reg 8 $ data_in [7:0] $end
$var reg 8 % data_out [7:0] $end
$var reg 16 & address_out [15:0] $end
$scope module cpu6502 $end
$var integer 32 ' instruction_register $end
$var integer 32 ( current_instr_state $end
$scope module RegAccumulator $end
$var reg 8 1 current_value [7:0] $end
$upscope $end
$upscope $end
$upscope $end
$enddefinitions $end
#0
b1 !
b1 "
b1 #
b11101010 $
b11101010 %
b0 &
b0 '
bx1 (
b0 1
b1 #
b11101010 %
b0 1
bx1 (
b0 '
b0 &
#10
b0 !
#20
b1 !
b0 "
#30
b0 !
#40
b1 !
b10101001 $
b10101001 %
bx (
bx '
b1 &
#50
b0 !
#60
b1 !
bx1 (
b10 &
#70
b0 !
#80
b1 !
b100000 $
b100000 %
bx (
bx0xxxxxx '
b11 &
#90
b0 !
#100
b1 !
b1101001 $
b1101001 %
b100000 1
bx1 (
b100 &
#110
b0 !
#120
b1 !
b101 $
b101 %
bx (
bx '
b101 &
#130
b0 !
#140
b1 !
bx0xx (
b110 &
b100000 %
#150
b0 !
#160
b1 !
bx0xx (
#170
b0 !
#180
b1 !
bx0xx (
b100101 %
#190
b0 !
#200
b1 !
b100101 1
bx1 (
b101 %
#210
b0 !
#220
b1 !
bx (
bx '
b111 &
#230
b0 !
#240
b1 !
b1000 &
#250
b0 !
#260
b1 !
b1001 &
#270
b0 !
#280
b1 !
b1010 &
#290
b0 !
#300
b1 !
b1011 &
#310
b0 !
#320
b1 !
