quartus/synthesis/program_counter.sv
module program_counter (
    input wire [7:0] PCL_in,
    input wire [7:0] PCH_in,

    input wire clk,
    input wire inc_enable,
    input wire load,
    input wire reset,

    output wire [7:0] PCL_out,
    output wire [7:0] PCH_out

);

  reg [15:0] current_pc;

  assign PCL_out = current_pc[7:0];
  assign PCH_out = current_pc[15:8];

  always @(posedge clk) begin

    if (reset) begin
      current_pc <= 16'h0;
    end else if (load) begin
      current_pc <= {PCH_in, PCL_in};
    end else begin
      if (inc_enable) begin
        current_pc <= current_pc + 1'b1;
      end else begin
        current_pc <= current_pc;
      end
    end
  end

endmodule

quartus/testbenches/program_counter.test.sv
`timescale 1ns / 1ps

module program_counter_test ();

  logic [7:0] PCL_in;
  logic [7:0] PCH_in;
  logic clk;
  logic inc_enable;
  logic load;
  logic reset;

  logic [7:0] PCL_out;
  logic [7:0] PCH_out;

  program_counter pc (
      .PCL_in(PCL_in),
      .PCH_in(PCH_in),
      .clk(clk),
      .inc_enable(inc_enable),
      .load(load),
      .reset(reset),
      .PCL_out(PCL_out),
      .PCH_out(PCH_out)
  );

  initial clk = 1;

  always #10 clk = ~clk;

  initial begin
    inc_enable = 1'b1;
    load = 1'b0;
    reset = 1;
    PCL_in = 8'h3f;
    PCH_in = 8'hfe;
    repeat (1) @(posedge clk);
    reset = 0;

    repeat (2) @(posedge clk);
    inc_enable = 0;
    load = 1;
    repeat (1) @(posedge clk);
    inc_enable = 1;
    load = 0;

    repeat (8) @(posedge clk);
    inc_enable = 0;

    repeat (2) @(posedge clk);
    $stop;
  end
endmodule

quartus/waveforms/pc.vcd
$date
	Tue Jul 16 21:20:25 2024
$end
$version
	ModelSim Version 2020.1
$end
$timescale
	1ps
$end
$scope module program_counter_test $end
$var reg 1 ! clk $end
$var reg 1 " inc_enable $end
$var reg 1 # load $end
$var reg 8 $ PCH_in [7:0] $end
$var reg 8 % PCH_out [7:0] $end
$var reg 8 & PCL_in [7:0] $end
$var reg 8 ' PCL_out [7:0] $end
$var reg 1 ( reset $end
$upscope $end
$enddefinitions $end
#0
b1 !
b1 "
b0 #
b11111110 $
b0 %
b111111 &
b0 '
b1 (
b0 %
b0 '
#10000
b0 !
#20000
b1 !
b0 (
#30000
b0 !
#40000
b1 !
b1 '
#50000
b0 !
#60000
b1 !
b0 "
b1 #
b10 '
#70000
b0 !
#80000
b1 !
b1 "
b0 #
b11111110 %
b111111 '
#90000
b0 !
#100000
b1 !
b1000000 '
#110000
b0 !
#120000
b1 !
b1000001 '
#130000
b0 !
#140000
b1 !
b1000010 '
#150000
b0 !
#160000
b1 !
b1000011 '
#170000
b0 !
#180000
b1 !
b1000100 '
#190000
b0 !
#200000
b1 !
b1000101 '
#210000
b0 !
#220000
b1 !
b1000110 '
#230000
b0 !
#240000
b1 !
b0 "
b1000111 '
#250000
b0 !
#260000
b1 !
#270000
b0 !
#280000
b1 !
