quartus/synthesis/register.sv
module register (
    input  logic [7:0] data_in,
    output logic [7:0] data_out,

    input logic clk,
    input logic load,
    input logic reset
);
  reg [7:0] current_value;

  always @(posedge clk) begin
    if (reset) begin
      current_value <= 8'b0;
    end else if (load) begin
      current_value <= data_in;
    end else begin
      current_value <= current_value;
    end
  end

  assign data_out = current_value;

endmodule

quartus/testbenches/register.test.sv
module register_test ();
  logic clk;
  initial clk = 1;
  always #10 clk = ~clk;

  logic [7:0] data_in, data_out;
  logic load, reset;

  register register (
      .data_in (data_in),
      .data_out(data_out),
      .clk     (clk),
      .load    (load),
      .reset   (reset)
  );

  initial begin
    reset = 1;
    load = 0;
    data_in = 8'hea;
    repeat (1) @(posedge clk);
    reset = 0;
    load  = 1;
    repeat (1) @(posedge clk);
    load = 0;
    repeat (2) @(posedge clk);

    $stop;
  end

endmodule

quartus/waveforms/register.vcd
$date
	Wed Jul 17 19:56:05 2024
$end
$version
	ModelSim Version 2020.1
$end
$timescale
	1ns
$end
$scope module register_test $end
$var reg 1 ! clk $end
$var reg 1 " reset $end
$var reg 1 # load $end
$var reg 8 $ data_in [7:0] $end
$var reg 8 % data_out [7:0] $end
$upscope $end
$enddefinitions $end
#0
b1 "
b0 #
b0 %
b11101010 $
b1 !
b0 %
#10
b0 !
#20
b1 !
b0 "
b1 #
#30
b0 !
#40
b1 !
b0 #
b11101010 %
#50
b0 !
#60
b1 !
#70
b0 !
#80
b1 !
